hologram/__init__.py
hologram/helpers.py
hologram/py.typed
hologram-0.0.16.dist-info/LICENSE
hologram-0.0.16.dist-info/METADATA
hologram-0.0.16.dist-info/WHEEL
hologram-0.0.16.dist-info/top_level.txt
hologram-0.0.16.dist-info/RECORD
