Metadata-Version: 2.1
Name: hologram
Version: 0.0.16
Summary: JSON schema generation from dataclasses
Home-page: https://github.com/fishtown-analytics/hologram
Author: Connor McArthur, Jacob Beck, Simon Knibbs
Author-email: info@fishtowanalytics.com, simon.knibbs@gmail.com
License: MIT
Platform: UNKNOWN
Classifier: Development Status :: 4 - Beta
Classifier: Intended Audience :: Developers
Classifier: License :: OSI Approved :: MIT License
Classifier: Programming Language :: Python
Classifier: Programming Language :: Python :: 3.6
Classifier: Programming Language :: Python :: 3.7
Classifier: Programming Language :: Python :: 3.8
Classifier: Programming Language :: Python :: 3.9
Classifier: Topic :: Software Development :: Libraries
